RTL_code/code4_processing_element.v
module code4_processing_element(
input [3:0] a_in , b_in,
input clk , rst ,
output reg [30:0]acc_sum,
output [3:0] a_out,b_out );
reg [3:0] aout ;
reg [3:0] bout ;

always @(posedge clk ) begin 
if (rst ) begin 
aout <= 0 ;
bout <= 0 ; 
acc_sum <= 0 ;end 

else begin 
acc_sum <= acc_sum + ( a_in * b_in );
aout <= a_in ;
bout <= b_in ;
end 
end 

assign a_out = aout ;
assign b_out = bout ;
endmodule

RTL_code/code6_top_pe_2x2.v
module code6_top_pe_2x2(
input clk , rst ,
input [3:0] A_in_0,A_in_1,
input [3:0] B_in_0,B_in_1,
output [30:0]s1, s2,s3, s4 );

wire [3:0] in1_a_out;
wire [3:0] in1_b_out;
wire [3:0] in2_a_out;
wire [3:0] in2_b_out;
wire [3:0] in3_a_out;
wire [3:0] in3_b_out;
wire [3:0] in4_a_out;
wire [3:0] in4_b_out;
wire [30:0] in1_acc_sum ;
wire [30:0] in2_acc_sum ;
wire [30:0] in3_acc_sum ;
wire [30:0] in4_acc_sum ;

/*
          B_in_0    B_in_1
            |         |
A_in_0 -> [PE1] -> [PE2]
           |         |
A_in_1 -> [PE3] -> [PE4]
*/
// onw just get the wire and cinnect them 

code4_processing_element PE1 (.clk(clk),.rst(rst),.a_in(A_in_0),.b_in(B_in_0),.a_out(in1_a_out),.b_out(in1_b_out),.acc_sum(in1_acc_sum));
code4_processing_element PE2 (.clk(clk),.rst(rst),.a_in(in1_a_out),.b_in(B_in_1),.a_out(in2_a_out),.b_out(in2_b_out),.acc_sum(in2_acc_sum));
code4_processing_element PE3 (.clk(clk),.rst(rst),.a_in(A_in_1),.b_in(in1_b_out),.a_out(in3_a_out),.b_out(in3_b_out),.acc_sum(in3_acc_sum));
code4_processing_element PE4 (.clk(clk),.rst(rst),.a_in(in3_a_out),.b_in(in2_b_out),.a_out(in4_a_out),.b_out(in4_b_out),.acc_sum(in4_acc_sum));


assign s1 = in1_acc_sum;
assign s2 = in2_acc_sum;
assign s3 = in3_acc_sum;
assign s4 = in4_acc_sum;

endmodule 

// ok this is done now pipelining is done and flow is also according to dig

RTL_code/top_pe_2x2_tb.v
module top_pe_2x2_tb ;
reg clk , rst ;
reg [3:0] A_in_0,A_in_1;
reg [3:0] B_in_0,B_in_1;
wire [30:0]s1 , s2 , s3 , s4;

/*
A = a00 a01     b = b00 b01
    a10 a11         b10 b11
*/

// now do multiply like we do in matrix 
//1st atrix row0 and 2nd matrix column 1 
// means a goes left to right and b goes to top to bottom 

// for now lets defing the variable manualluyy 

reg [3:0] a00 = 4'b1010, a01 = 4'b0010, a10 = 4'b1110, a11 = 4'b1011;
reg [3:0] b00 = 4'b1010, b01 = 4'b0010, b10 = 4'b1110, b11 = 4'b1011;

// now passing of them 
// feed them 1 by 1 to inputs of code6_top_pr_2x2
always #10 clk = ~clk; 
code6_top_pe_2x2 in (.clk(clk),.rst(rst),.A_in_0(A_in_0),.A_in_1(A_in_1),.B_in_0(B_in_0),.B_in_1(B_in_1),.s1(s1),.s2(s2),.s3(s3),.s4(s4));

initial begin 
    $dumpfile("pe_2x2.vcd");
    $dumpvars(0,top_pe_2x2_tb);

    clk = 0;        // Start with 0
    rst = 1;        // Reset ON
    #20;            // Wait
    rst = 0;        // Reset OFF (Now hardware is ready)

    // T1: Input 1
    A_in_0 = a00; B_in_0 = b00;
    A_in_1 = 0; B_in_1 = 0;
    #100; // Wait for next clock cycle

    // T2: Input 2 (Skewed)
    A_in_0 = a01; B_in_0 = b10;
    A_in_1 = a10; B_in_1 = b01;
    #100;

    // T3: Input 3
    A_in_0 = 0; B_in_0 = 0;
    A_in_1 = a11; B_in_1 = b11;
    #100;

    // T4: Ek extra clock cycle result capture karne ke liye
    #100; 
    
    $display("Results: s1=%d, s2=%d, s3=%d, s4=%d", s1, s2, s3, s4);
    $finish;
end
endmodule

RTL_code/pe_2x2.vcd
$date
	Wed Apr  1 11:48:04 2026
$end
$version
	Icarus Verilog
$end
$timescale
	1s
$end
$scope module top_pe_2x2_tb $end
$var wire 31 ! s4 [30:0] $end
$var wire 31 " s3 [30:0] $end
$var wire 31 # s2 [30:0] $end
$var wire 31 $ s1 [30:0] $end
$var reg 4 % A_in_0 [3:0] $end
$var reg 4 & A_in_1 [3:0] $end
$var reg 4 ' B_in_0 [3:0] $end
$var reg 4 ( B_in_1 [3:0] $end
$var reg 4 ) a00 [3:0] $end
$var reg 4 * a01 [3:0] $end
$var reg 4 + a10 [3:0] $end
$var reg 4 , a11 [3:0] $end
$var reg 4 - b00 [3:0] $end
$var reg 4 . b01 [3:0] $end
$var reg 4 / b10 [3:0] $end
$var reg 4 0 b11 [3:0] $end
$var reg 1 1 clk $end
$var reg 1 2 rst $end
$scope module in $end
$var wire 4 3 A_in_0 [3:0] $end
$var wire 4 4 A_in_1 [3:0] $end
$var wire 4 5 B_in_0 [3:0] $end
$var wire 4 6 B_in_1 [3:0] $end
$var wire 1 1 clk $end
$var wire 1 2 rst $end
$var wire 31 7 s1 [30:0] $end
$var wire 31 8 s2 [30:0] $end
$var wire 31 9 s3 [30:0] $end
$var wire 31 : s4 [30:0] $end
$var wire 4 ; in4_b_out [3:0] $end
$var wire 31 < in4_acc_sum [30:0] $end
$var wire 4 = in4_a_out [3:0] $end
$var wire 4 > in3_b_out [3:0] $end
$var wire 31 ? in3_acc_sum [30:0] $end
$var wire 4 @ in3_a_out [3:0] $end
$var wire 4 A in2_b_out [3:0] $end
$var wire 31 B in2_acc_sum [30:0] $end
$var wire 4 C in2_a_out [3:0] $end
$var wire 4 D in1_b_out [3:0] $end
$var wire 31 E in1_acc_sum [30:0] $end
$var wire 4 F in1_a_out [3:0] $end
$scope module PE1 $end
$var wire 4 G a_in [3:0] $end
$var wire 4 H a_out [3:0] $end
$var wire 4 I b_in [3:0] $end
$var wire 4 J b_out [3:0] $end
$var wire 1 1 clk $end
$var wire 1 2 rst $end
$var reg 31 K acc_sum [30:0] $end
$var reg 4 L aout [3:0] $end
$var reg 4 M bout [3:0] $end
$upscope $end
$scope module PE2 $end
$var wire 4 N a_in [3:0] $end
$var wire 4 O a_out [3:0] $end
$var wire 4 P b_in [3:0] $end
$var wire 4 Q b_out [3:0] $end
$var wire 1 1 clk $end
$var wire 1 2 rst $end
$var reg 31 R acc_sum [30:0] $end
$var reg 4 S aout [3:0] $end
$var reg 4 T bout [3:0] $end
$upscope $end
$scope module PE3 $end
$var wire 4 U a_in [3:0] $end
$var wire 4 V a_out [3:0] $end
$var wire 4 W b_in [3:0] $end
$var wire 4 X b_out [3:0] $end
$var wire 1 1 clk $end
$var wire 1 2 rst $end
$var reg 31 Y acc_sum [30:0] $end
$var reg 4 Z aout [3:0] $end
$var reg 4 [ bout [3:0] $end
$upscope $end
$scope module PE4 $end
$var wire 4 \ a_in [3:0] $end
$var wire 4 ] a_out [3:0] $end
$var wire 4 ^ b_in [3:0] $end
$var wire 4 _ b_out [3:0] $end
$var wire 1 1 clk $end
$var wire 1 2 rst $end
$var reg 31 ` acc_sum [30:0] $end
$var reg 4 a aout [3:0] $end
$var reg 4 b bout [3:0] $end
$upscope $end
$upscope $end
$upscope $end
$enddefinitions $end
#0
$dumpvars
bx b
bx a
bx `
bx _
bx ^
bx ]
bx \
bx [
bx Z
bx Y
bx X
bx W
bx V
bx U
bx T
bx S
bx R
bx Q
bx P
bx O
bx N
bx M
bx L
bx K
bx J
bx I
bx H
bx G
bx F
bx E
bx D
bx C
bx B
bx A
bx @
bx ?
bx >
bx =
bx <
bx ;
bx :
bx 9
bx 8
bx 7
bx 6
bx 5
bx 4
bx 3
12
01
b1011 0
b1110 /
b10 .
b1010 -
b1011 ,
b1110 +
b10 *
b1010 )
bx (
bx '
bx &
bx %
bx $
bx #
bx "
bx !
$end
#10
b0 $
b0 7
b0 E
b0 K
b0 D
b0 J
b0 W
b0 M
b0 F
b0 H
b0 N
b0 L
b0 #
b0 8
b0 B
b0 R
b0 A
b0 Q
b0 ^
b0 T
b0 C
b0 O
b0 S
b0 "
b0 9
b0 ?
b0 Y
b0 >
b0 X
b0 [
b0 @
b0 V
b0 \
b0 Z
b0 !
b0 :
b0 <
b0 `
b0 ;
b0 _
b0 b
b0 =
b0 ]
b0 a
11
#20
01
b0 (
b0 6
b0 P
b0 &
b0 4
b0 U
b1010 '
b1010 5
b1010 I
b1010 %
b1010 3
b1010 G
02
#30
b1010 D
b1010 J
b1010 W
b1010 M
b1010 F
b1010 H
b1010 N
b1010 L
b1100100 $
b1100100 7
b1100100 E
b1100100 K
11
#40
01
#50
b11001000 $
b11001000 7
b11001000 E
b11001000 K
b1010 C
b1010 O
b1010 S
b1010 >
b1010 X
b1010 [
11
#60
01
#70
b100101100 $
b100101100 7
b100101100 E
b100101100 K
11
#80
01
#90
b110010000 $
b110010000 7
b110010000 E
b110010000 K
11
#100
01
#110
b111110100 $
b111110100 7
b111110100 E
b111110100 K
11
#120
01
b10 (
b10 6
b10 P
b1110 &
b1110 4
b1110 U
b1110 '
b1110 5
b1110 I
b10 %
b10 3
b10 G
#130
b1110 D
b1110 J
b1110 W
b1110 M
b10 F
b10 H
b10 N
b10 L
b1000010000 $
b1000010000 7
b1000010000 E
b1000010000 K
b10 A
b10 Q
b10 ^
b10 T
b10100 #
b10100 8
b10100 B
b10100 R
b1110 @
b1110 V
b1110 \
b1110 Z
b10001100 "
b10001100 9
b10001100 ?
b10001100 Y
11
#140
01
#150
b10 ;
b10 _
b10 b
b1110 =
b1110 ]
b1110 a
b11100 !
b11100 :
b11100 <
b11100 `
b1110 >
b1110 X
b1110 [
b101010000 "
b101010000 9
b101010000 ?
b101010000 Y
b10 C
b10 O
b10 S
b11000 #
b11000 8
b11000 B
b11000 R
b1000101100 $
b1000101100 7
b1000101100 E
b1000101100 K
11
#160
01
#170
b1001001000 $
b1001001000 7
b1001001000 E
b1001001000 K
b11100 #
b11100 8
b11100 B
b11100 R
b1000010100 "
b1000010100 9
b1000010100 ?
b1000010100 Y
b111000 !
b111000 :
b111000 <
b111000 `
11
#180
01
#190
b1010100 !
b1010100 :
b1010100 <
b1010100 `
b1011011000 "
b1011011000 9
b1011011000 ?
b1011011000 Y
b100000 #
b100000 8
b100000 B
b100000 R
b1001100100 $
b1001100100 7
b1001100100 E
b1001100100 K
11
#200
01
#210
b1010000000 $
b1010000000 7
b1010000000 E
b1010000000 K
b100100 #
b100100 8
b100100 B
b100100 R
b1110011100 "
b1110011100 9
b1110011100 ?
b1110011100 Y
b1110000 !
b1110000 :
b1110000 <
b1110000 `
11
#220
01
b1011 (
b1011 6
b1011 P
b1011 &
b1011 4
b1011 U
b0 '
b0 5
b0 I
b0 %
b0 3
b0 G
#230
b10001100 !
b10001100 :
b10001100 <
b10001100 `
b1011 @
b1011 V
b1011 \
b1011 Z
b10000110110 "
b10000110110 9
b10000110110 ?
b10000110110 Y
b1011 A
b1011 Q
b1011 ^
b1011 T
b111010 #
b111010 8
b111010 B
b111010 R
b0 D
b0 J
b0 W
b0 M
b0 F
b0 H
b0 N
b0 L
11
#240
01
#250
b0 C
b0 O
b0 S
b0 >
b0 X
b0 [
b1011 ;
b1011 _
b1011 b
b1011 =
b1011 ]
b1011 a
b100000101 !
b100000101 :
b100000101 <
b100000101 `
11
#260
01
#270
b101111110 !
b101111110 :
b101111110 <
b101111110 `
11
#280
01
#290
b111110111 !
b111110111 :
b111110111 <
b111110111 `
11
#300
01
#310
b1001110000 !
b1001110000 :
b1001110000 <
b1001110000 `
11
#320
01
#330
b1011101001 !
b1011101001 :
b1011101001 <
b1011101001 `
11
#340
01
#350
b1101100010 !
b1101100010 :
b1101100010 <
b1101100010 `
11
#360
01
#370
b1111011011 !
b1111011011 :
b1111011011 <
b1111011011 `
11
#380
01
#390
b10001010100 !
b10001010100 :
b10001010100 <
b10001010100 `
11
#400
01
#410
b10011001101 !
b10011001101 :
b10011001101 <
b10011001101 `
11
