RTL_code/code4_processing_element.v
module code4_processing_element(
input [3:0] a_in , b_in,
input clk , rst ,
input valid ,// this is added to tell the MAC to when to start multply and when to add 
output reg [30:0]acc_sum,
output [3:0] a_out,b_out,
output reg v_out );
reg [3:0] aout ;
reg [3:0] bout ;

always @(posedge clk ) begin 
if (rst ) begin 
aout <= 0 ;
bout <= 0 ; 
acc_sum <= 0 ;end 

else begin 
aout <= a_in ;
bout <= b_in ;
v_out <= valid;
if (valid == 1 )begin
acc_sum <= acc_sum + ( a_in * b_in );
end
else begin 
 acc_sum <= acc_sum;end
end 
end 

assign a_out = aout ;
assign b_out = bout ;
endmodule

RTL_code/code6_top_pe_2x2.v
module code6_top_pe_2x2(
input clk , rst ,
input [3:0] A_in_0,A_in_1,
input [3:0] B_in_0,B_in_1,
output [30:0]s1, s2,s3, s4 ,
input valid  );

wire [3:0] in1_a_out;
wire [3:0] in1_b_out;
wire [3:0] in2_a_out;
wire [3:0] in2_b_out;
wire [3:0] in3_a_out;
wire [3:0] in3_b_out;
wire [3:0] in4_a_out;
wire [3:0] in4_b_out;
wire [30:0] in1_acc_sum ;
wire [30:0] in2_acc_sum ;
wire [30:0] in3_acc_sum ;
wire [30:0] in4_acc_sum ;
wire v1_out , v2_out ,v3_out ,v4_out;

/*
          B_in_0    B_in_1
            |         |
A_in_0 -> [PE1] -> [PE2]
           |         |
A_in_1 -> [PE3] -> [PE4]
*/
// onw just get the wire and cinnect them 

code4_processing_element PE1 (.clk(clk),.rst(rst),.a_in(A_in_0),.b_in(B_in_0),.a_out(in1_a_out),.b_out(in1_b_out),.acc_sum(in1_acc_sum),.valid(valid ),.v_out(v1_out));
code4_processing_element PE2 (.clk(clk),.rst(rst),.a_in(in1_a_out),.b_in(B_in_1),.a_out(in2_a_out),.b_out(in2_b_out),.acc_sum(in2_acc_sum),.valid(v1_out),.v_out(v2_out));
code4_processing_element PE3 (.clk(clk),.rst(rst),.a_in(A_in_1),.b_in(in1_b_out),.a_out(in3_a_out),.b_out(in3_b_out),.acc_sum(in3_acc_sum),.valid(v1_out),.v_out(v3_out));
code4_processing_element PE4 (.clk(clk),.rst(rst),.a_in(in3_a_out),.b_in(in2_b_out),.a_out(in4_a_out),.b_out(in4_b_out),.acc_sum(in4_acc_sum),.valid(v3_out),.v_out(v4_out));


assign s1 = in1_acc_sum;
assign s2 = in2_acc_sum;
assign s3 = in3_acc_sum;
assign s4 = in4_acc_sum;

endmodule 

// ok this is done now pipelining is done and flow is also according to dig

RTL_code/top_pe_2x2_tb.v
module top_pe_2x2_tb ;
reg clk , rst ;
reg valid ;
reg [3:0] A_in_0,A_in_1;
reg [3:0] B_in_0,B_in_1;
wire [30:0]s1 , s2 , s3 , s4;

/*
A = a00 a01     b = b00 b01
    a10 a11         b10 b11
*/

// now do multiply like we do in matrix 
//1st atrix row0 and 2nd matrix column 1 
// means a goes left to right and b goes to top to bottom 

// for now lets defing the variable manualluyy 

reg [3:0] a00 = 4'b1010, a01 = 4'b0010, a10 = 4'b1110, a11 = 4'b1011;
reg [3:0] b00 = 4'b1010, b01 = 4'b0010, b10 = 4'b1110, b11 = 4'b1011;

// now passing of them 
// feed them 1 by 1 to inputs of code6_top_pr_2x2
always #10 clk = ~clk; 
code6_top_pe_2x2 in (.clk(clk),.rst(rst),.A_in_0(A_in_0),.A_in_1(A_in_1),.B_in_0(B_in_0),.B_in_1(B_in_1),.s1(s1),.s2(s2),.s3(s3),.s4(s4),.valid(valid));

initial begin 
    $dumpfile("pe_2x2.vcd");
    $dumpvars(0,top_pe_2x2_tb);

    clk = 0;        // Start with 0
    rst = 1;        // Reset ON
    #25;            // Wait
    rst = 0;        // Reset OFF (Now hardware is ready)
    valid = 0 ;
    // T1: Input 1
    @(posedge clk);
    #2;
       A_in_0 = a00; B_in_0 = b00;
    A_in_1 = 0; B_in_1 = 0; valid = 1 ;
     // Wait for next clock cycle

    // T2: Input 2 (Skewed)
    @(posedge clk);
    #2;
    A_in_0 = a01; B_in_0 = b10;
    A_in_1 = a10; B_in_1 = b01;
    

    // T3: Input 3
    @(posedge clk);
    #2;
    A_in_0 = 0; B_in_0 = 0;
    A_in_1 = a11; B_in_1 = b11;
    

    // T4: Ek extra clock cycle result capture karne ke liye
    @(posedge clk);
    #2;
    A_in_0 = 0 ;B_in_0=0;
    A_in_1 = 0 ;B_in_1 = 0 ; valid = 0 ;
    #100;
    $display("Results: s1=%d, s2=%d, s3=%d, s4=%d", s1, s2, s3, s4);
    $finish;
end
endmodule

RTL_code/pe_2x2.vcd
$date
	Thu Apr  2 10:29:59 2026
$end
$version
	Icarus Verilog
$end
$timescale
	1s
$end
$scope module top_pe_2x2_tb $end
$var wire 31 ! s4 [30:0] $end
$var wire 31 " s3 [30:0] $end
$var wire 31 # s2 [30:0] $end
$var wire 31 $ s1 [30:0] $end
$var reg 4 % A_in_0 [3:0] $end
$var reg 4 & A_in_1 [3:0] $end
$var reg 4 ' B_in_0 [3:0] $end
$var reg 4 ( B_in_1 [3:0] $end
$var reg 4 ) a00 [3:0] $end
$var reg 4 * a01 [3:0] $end
$var reg 4 + a10 [3:0] $end
$var reg 4 , a11 [3:0] $end
$var reg 4 - b00 [3:0] $end
$var reg 4 . b01 [3:0] $end
$var reg 4 / b10 [3:0] $end
$var reg 4 0 b11 [3:0] $end
$var reg 1 1 clk $end
$var reg 1 2 rst $end
$var reg 1 3 valid $end
$scope module in $end
$var wire 4 4 A_in_0 [3:0] $end
$var wire 4 5 A_in_1 [3:0] $end
$var wire 4 6 B_in_0 [3:0] $end
$var wire 4 7 B_in_1 [3:0] $end
$var wire 1 1 clk $end
$var wire 1 2 rst $end
$var wire 31 8 s1 [30:0] $end
$var wire 31 9 s2 [30:0] $end
$var wire 31 : s3 [30:0] $end
$var wire 31 ; s4 [30:0] $end
$var wire 1 3 valid $end
$var wire 1 < v4_out $end
$var wire 1 = v3_out $end
$var wire 1 > v2_out $end
$var wire 1 ? v1_out $end
$var wire 4 @ in4_b_out [3:0] $end
$var wire 31 A in4_acc_sum [30:0] $end
$var wire 4 B in4_a_out [3:0] $end
$var wire 4 C in3_b_out [3:0] $end
$var wire 31 D in3_acc_sum [30:0] $end
$var wire 4 E in3_a_out [3:0] $end
$var wire 4 F in2_b_out [3:0] $end
$var wire 31 G in2_acc_sum [30:0] $end
$var wire 4 H in2_a_out [3:0] $end
$var wire 4 I in1_b_out [3:0] $end
$var wire 31 J in1_acc_sum [30:0] $end
$var wire 4 K in1_a_out [3:0] $end
$scope module PE1 $end
$var wire 4 L a_in [3:0] $end
$var wire 4 M a_out [3:0] $end
$var wire 4 N b_in [3:0] $end
$var wire 4 O b_out [3:0] $end
$var wire 1 1 clk $end
$var wire 1 2 rst $end
$var wire 1 3 valid $end
$var reg 31 P acc_sum [30:0] $end
$var reg 4 Q aout [3:0] $end
$var reg 4 R bout [3:0] $end
$var reg 1 ? v_out $end
$upscope $end
$scope module PE2 $end
$var wire 4 S a_in [3:0] $end
$var wire 4 T a_out [3:0] $end
$var wire 4 U b_in [3:0] $end
$var wire 4 V b_out [3:0] $end
$var wire 1 1 clk $end
$var wire 1 2 rst $end
$var wire 1 ? valid $end
$var reg 31 W acc_sum [30:0] $end
$var reg 4 X aout [3:0] $end
$var reg 4 Y bout [3:0] $end
$var reg 1 > v_out $end
$upscope $end
$scope module PE3 $end
$var wire 4 Z a_in [3:0] $end
$var wire 4 [ a_out [3:0] $end
$var wire 4 \ b_in [3:0] $end
$var wire 4 ] b_out [3:0] $end
$var wire 1 1 clk $end
$var wire 1 2 rst $end
$var wire 1 ? valid $end
$var reg 31 ^ acc_sum [30:0] $end
$var reg 4 _ aout [3:0] $end
$var reg 4 ` bout [3:0] $end
$var reg 1 = v_out $end
$upscope $end
$scope module PE4 $end
$var wire 4 a a_in [3:0] $end
$var wire 4 b a_out [3:0] $end
$var wire 4 c b_in [3:0] $end
$var wire 4 d b_out [3:0] $end
$var wire 1 1 clk $end
$var wire 1 2 rst $end
$var wire 1 = valid $end
$var reg 31 e acc_sum [30:0] $end
$var reg 4 f aout [3:0] $end
$var reg 4 g bout [3:0] $end
$var reg 1 < v_out $end
$upscope $end
$upscope $end
$upscope $end
$enddefinitions $end
#0
$dumpvars
bx g
bx f
bx e
bx d
bx c
bx b
bx a
bx `
bx _
bx ^
bx ]
bx \
bx [
bx Z
bx Y
bx X
bx W
bx V
bx U
bx T
bx S
bx R
bx Q
bx P
bx O
bx N
bx M
bx L
bx K
bx J
bx I
bx H
bx G
bx F
bx E
bx D
bx C
bx B
bx A
bx @
x?
x>
x=
x<
bx ;
bx :
bx 9
bx 8
bx 7
bx 6
bx 5
bx 4
x3
12
01
b1011 0
b1110 /
b10 .
b1010 -
b1011 ,
b1110 +
b10 *
b1010 )
bx (
bx '
bx &
bx %
bx $
bx #
bx "
bx !
$end
#10
b0 $
b0 8
b0 J
b0 P
b0 I
b0 O
b0 \
b0 R
b0 K
b0 M
b0 S
b0 Q
b0 #
b0 9
b0 G
b0 W
b0 F
b0 V
b0 c
b0 Y
b0 H
b0 T
b0 X
b0 "
b0 :
b0 D
b0 ^
b0 C
b0 ]
b0 `
b0 E
b0 [
b0 a
b0 _
b0 !
b0 ;
b0 A
b0 e
b0 @
b0 d
b0 g
b0 B
b0 b
b0 f
11
#20
01
#25
03
02
#30
bx E
bx [
bx a
bx _
bx F
bx V
bx c
bx Y
0?
bx I
bx O
bx \
bx R
bx K
bx M
bx S
bx Q
11
#32
13
b0 (
b0 7
b0 U
b0 &
b0 5
b0 Z
b1010 '
b1010 6
b1010 N
b1010 %
b1010 4
b1010 L
#40
01
#50
b1100100 $
b1100100 8
b1100100 J
b1100100 P
1?
b1010 I
b1010 O
b1010 \
b1010 R
b1010 K
b1010 M
b1010 S
b1010 Q
0>
b0 F
b0 V
b0 c
b0 Y
bx H
bx T
bx X
0=
bx C
bx ]
bx `
b0 E
b0 [
b0 a
b0 _
bx @
bx d
bx g
bx B
bx b
bx f
11
#52
b10 (
b10 7
b10 U
b1110 &
b1110 5
b1110 Z
b1110 '
b1110 6
b1110 N
b10 %
b10 4
b10 L
#60
01
#70
0<
b0 @
b0 d
b0 g
b0 B
b0 b
b0 f
b10001100 "
b10001100 :
b10001100 D
b10001100 ^
1=
b1010 C
b1010 ]
b1010 `
b1110 E
b1110 [
b1110 a
b1110 _
b10100 #
b10100 9
b10100 G
b10100 W
1>
b10 F
b10 V
b10 c
b10 Y
b1010 H
b1010 T
b1010 X
b10000000 $
b10000000 8
b10000000 J
b10000000 P
b1110 I
b1110 O
b1110 \
b1110 R
b10 K
b10 M
b10 S
b10 Q
11
#72
b1011 (
b1011 7
b1011 U
b1011 &
b1011 5
b1011 Z
b0 '
b0 6
b0 N
b0 %
b0 4
b0 L
#80
01
#90
b0 I
b0 O
b0 \
b0 R
b0 K
b0 M
b0 S
b0 Q
b101010 #
b101010 9
b101010 G
b101010 W
b1011 F
b1011 V
b1011 c
b1011 Y
b10 H
b10 T
b10 X
b100100110 "
b100100110 :
b100100110 D
b100100110 ^
b1110 C
b1110 ]
b1110 `
b1011 E
b1011 [
b1011 a
b1011 _
b11100 !
b11100 ;
b11100 A
b11100 e
1<
b10 @
b10 d
b10 g
b1110 B
b1110 b
b1110 f
11
#92
03
b0 (
b0 7
b0 U
b0 &
b0 5
b0 Z
#100
01
#110
b10010101 !
b10010101 ;
b10010101 A
b10010101 e
b1011 @
b1011 d
b1011 g
b1011 B
b1011 b
b1011 f
b0 C
b0 ]
b0 `
b0 E
b0 [
b0 a
b0 _
b0 F
b0 V
b0 c
b0 Y
b0 H
b0 T
b0 X
0?
11
#120
01
#130
0>
0=
b0 @
b0 d
b0 g
b0 B
b0 b
b0 f
11
#140
01
#150
0<
11
